pipetee/__init__.py
pipetee/pipeline.py
pipetee/py.typed
pipetee/models/__init__.py
pipetee/models/checkpoint.py
pipetee/models/stage.py
pipetee/models/visual.py
pipetee/utils/logging_config.py
pipetee/utils/visualization.py
pipetee-0.3.0.dist-info/METADATA
pipetee-0.3.0.dist-info/WHEEL
pipetee-0.3.0.dist-info/licenses/LICENSE
pipetee-0.3.0.dist-info/RECORD
